bacolonyzer/__init__.py
bacolonyzer/__main__.py
bacolonyzer/analysis.py
bacolonyzer/filesystem.py
bacolonyzer/image_processing.py
bacolonyzer/utils.py
bacolonyzer/commands/__init__.py
bacolonyzer/commands/abstract.py
bacolonyzer/commands/analyse.py
bacolonyzer/commands/entrypoint.py
bacolonyzer/commands/rename_images.py
bacolonyzer/commands/stabilize_images.py
bacolonyzer-2.0.10.dist-info/LICENSE
bacolonyzer-2.0.10.dist-info/METADATA
bacolonyzer-2.0.10.dist-info/WHEEL
bacolonyzer-2.0.10.dist-info/entry_points.txt
bacolonyzer-2.0.10.dist-info/top_level.txt
bacolonyzer-2.0.10.dist-info/RECORD
